browniebroke_utils/__init__.py
browniebroke_utils/py.typed
browniebroke_utils/setup_prettier.py
browniebroke_utils/setup_pywatchers.py
browniebroke_utils/setup_ruffwatcher.py
browniebroke_utils-1.4.0.dist-info/licenses/LICENSE
browniebroke_utils-1.4.0.dist-info/METADATA
browniebroke_utils-1.4.0.dist-info/WHEEL
browniebroke_utils-1.4.0.dist-info/entry_points.txt
browniebroke_utils-1.4.0.dist-info/top_level.txt
browniebroke_utils-1.4.0.dist-info/RECORD
