Metadata-Version: 2.4
Name: browniebroke-utils
Version: 1.4.0
Summary: A collections of small scripts.
Author-email: Bruno Alla <alla.brunoo@gmail.com>
License-Expression: MIT
Project-URL: Bug Tracker, https://github.com/browniebroke/browniebroke-utils/issues
Project-URL: Changelog, https://github.com/browniebroke/browniebroke-utils/blob/main/CHANGELOG.md
Project-URL: Mastodon, https://fosstodon.org/@browniebroke
Project-URL: repository, https://github.com/browniebroke/browniebroke-utils
Project-URL: Twitter, https://twitter.com/_BrunoAlla
Classifier: Development Status :: 3 - Alpha
Classifier: Intended Audience :: Developers
Classifier: Natural Language :: English
Classifier: Operating System :: OS Independent
Classifier: Programming Language :: Python :: 3 :: Only
Classifier: Programming Language :: Python :: 3.10
Classifier: Programming Language :: Python :: 3.11
Classifier: Programming Language :: Python :: 3.12
Classifier: Programming Language :: Python :: 3.13
Classifier: Programming Language :: Python :: 3.14
Classifier: Topic :: Software Development :: Libraries
Requires-Python: >=3.10
License-File: LICENSE
Requires-Dist: xmltodict<2,>=1
Dynamic: license-file
